lineage_aq/__init__.py
lineage_aq/__main__.py
lineage_aq/config.py
lineage_aq/lineage.py
lineage_aq/my_io.py
lineage_aq/search.py
lineage_aq_py37-1.5.0.dist-info/LICENSE.md
lineage_aq_py37-1.5.0.dist-info/WHEEL
lineage_aq_py37-1.5.0.dist-info/METADATA
lineage_aq_py37-1.5.0.dist-info/entry_points.txt
lineage_aq_py37-1.5.0.dist-info/RECORD
