Metadata-Version: 2.1
Name: lineage-aq-py37
Version: 1.5.0
Summary: Interactive command line interface to create and edit lineage of families.
Home-page: https://github.com/aqdasak/Lineage/
License: MIT
Keywords: python,lineage,genealogy
Author: Aqdas Ahmad Khan
Author-email: aqdasak@gmail.com
Requires-Python: >=3.7,<4.0
Classifier: License :: OSI Approved :: MIT License
Classifier: Programming Language :: Python :: 3
Classifier: Programming Language :: Python :: 3.7
Classifier: Programming Language :: Python :: 3.8
Classifier: Programming Language :: Python :: 3.9
Classifier: Programming Language :: Python :: 3.10
Classifier: Programming Language :: Python :: 3.11
Requires-Dist: colorama (>=0.4.5,<0.5.0)
Requires-Dist: networkx (>=2.6.3,<3.0.0)
Requires-Dist: requests (>=2.31.0,<3.0.0)
Project-URL: Repository, https://github.com/aqdasak/Lineage/
